generic_api
